{
  "leastVersion":24,
  "broadCast":"",
  "versions":{
    "v0":{"type":"error", "message":"Must update"},
    "v1":{"type":"error", "message":"Must update"},
    "v2":{"type":"error", "message":"Must update"},
    "v3":{"type":"error", "message":"Must update"},
    "v4":{"type":"error", "message":"Must update"},
    "v5":{"type":"error", "message":"Must update"},
    "v16":{"type":"error", "message":"Must update"},
    "v17":{"type":"error", "message":"Must update"},
    "v18":{"type":"error", "message":"Must update download speed up"},
    "v19":{"type":"error", "message":"Must update"},
    "v20":{"type":"error", "message":"Must update"},
    "v21":{"type":"error", "message":"Must update"},
    "v22":{"type":"error", "message":"Must update"},
    "v23":{"type":"error", "message":"Must update"}
  }
}
